savex/__init__.py
savex/main.py
savex-0.1.0.dist-info/LICENSE
savex-0.1.0.dist-info/METADATA
savex-0.1.0.dist-info/WHEEL
savex-0.1.0.dist-info/top_level.txt
savex-0.1.0.dist-info/RECORD
