Metadata-Version: 2.1
Name: savex
Version: 0.1.0
Summary: Savex is a Python library crafted to bolster the security of file uploads within web applications. With an emphasis on mitigating prevalent vulnerabilities associated with file handling, Savex furnishes sturdy sanitization and validation capabilities to ensure that uploaded files are safe for utilization within your application.
Home-page: https://github.com/aliftech/savex
Author: Wahyu Krisna Aji
Author-email: wahyukrisnaaji32@gmail.com
License: MIT
Keywords: savex,file filtering,backdoor detection
Classifier: Operating System :: OS Independent
Classifier: License :: OSI Approved :: MIT License
Classifier: Programming Language :: Python :: 3
License-File: LICENSE
